mmb_layer0/__init__.py
mmb_layer0/config.py
mmb_layer0/blockchain/__init__.py
mmb_layer0/blockchain/chain/__init__.py
mmb_layer0/blockchain/chain/chain_repository_interface.py
mmb_layer0/blockchain/chain/chain_sync_services.py
mmb_layer0/blockchain/chain/json_chain_repository.py
mmb_layer0/blockchain/chain/local_saver.py
mmb_layer0/blockchain/chain/saver_impl/__init__.py
mmb_layer0/blockchain/chain/saver_impl/filebase_saver.py
mmb_layer0/blockchain/consensus/__init__.py
mmb_layer0/blockchain/consensus/consensus.py
mmb_layer0/blockchain/consensus/consensus_processor.py
mmb_layer0/blockchain/consensus/poa_consensus.py
mmb_layer0/blockchain/core/__init__.py
mmb_layer0/blockchain/core/block.py
mmb_layer0/blockchain/core/chain.py
mmb_layer0/blockchain/core/transaction_type.py
mmb_layer0/blockchain/core/validator.py
mmb_layer0/blockchain/core/worldstate.py
mmb_layer0/blockchain/processor/__init__.py
mmb_layer0/blockchain/processor/block_processor.py
mmb_layer0/blockchain/processor/transaction_processor.py
mmb_layer0/blockchain/worldstate/__init__.py
mmb_layer0/blockchain/worldstate/worldstate_sync_services.py
mmb_layer0/node/__init__.py
mmb_layer0/node/node.py
mmb_layer0/node/node_event_handler.py
mmb_layer0/node/node_sync_services.py
mmb_layer0/node/remote_node.py
mmb_layer0/node/events/EventHandler.py
mmb_layer0/node/events/__init__.py
mmb_layer0/node/events/node_event.py
mmb_layer0/node/events/impl/__init__.py
mmb_layer0/node/events/impl/chain_event/__init__.py
mmb_layer0/node/events/impl/chain_event/block_event.py
mmb_layer0/node/events/impl/chain_event/chain_head.py
mmb_layer0/node/events/impl/chain_event/full_chain.py
mmb_layer0/node/events/impl/chain_event/tx_event.py
mmb_layer0/node/events/impl/network_event/__init__.py
mmb_layer0/node/events/impl/network_event/peer_discovery_event.py
mmb_layer0/node/events/impl/network_event/ping_event.py
mmb_layer0/p2p/__init__.py
mmb_layer0/p2p/network.py
mmb_layer0/p2p/peer.py
mmb_layer0/p2p/protocol.py
mmb_layer0-1.0.5.dist-info/WHEEL
mmb_layer0-1.0.5.dist-info/METADATA
mmb_layer0-1.0.5.dist-info/RECORD
