Metadata-Version: 2.4
Name: mmb_layer0
Version: 1.0.5
Summary: MMB blockchain network
Author-email: Lee Min Waan <100744636+plsgivemeachane@users.noreply.github.com>
Requires-Python: >=3.10
Requires-Dist: rsa >=4.9.1,<5.0.0
Requires-Dist: ecdsa >=0.19.1,<0.20.0
Requires-Dist: jsonlight >=0.0.7,<0.0.8
Requires-Dist: rich >=14.0.0,<15.0.0
Requires-Dist: streamlit >=1.45.1,<2.0.0
